[
  {
    "id": "1",
    "name": "Christmas Live Event 1",
    "location": {
      "longitude": -79.870798,
      "latitude": 44.149035,
      "address": "www.themeetinghouse.com/live"
    },
    "serviceTimes": ["December 24 - 1:00pm"]
  },
  {
    "id": "2",
    "name": "Christmas Live Event 2",
    "location": {
      "longitude": -77.2674762,
      "latitude": 43.9188665,
      "address": "www.themeetinghouse.com/live"
    },
    "serviceTimes": ["December 24 - 4:00pm"]
  },

  {
    "id": "3",
    "name": "Christmas Live Event 3",
    "location": {
      "longitude": -79.8373778,
      "latitude": 43.2415413,
      "address": "www.themeetinghouse.com/live"
    },
    "serviceTimes": ["December 24 - 8:00pm"]
  }
]
