[
  {
    "FirstName": "Michael",
    "LastName": "Kotsopoulos",
    "sites": ["ALLI"],
    "Email": "michael.kotsopoulos@themeetinghouse.com",
    "Position": "Alliston Lead Pastor"
  },
  {
    "FirstName": "Amy",
    "LastName": "Thompson",
    "sites": ["ALLI"],
    "Email": "alliston.compassion@themeetinghouse.com",
    "Position": "Compassion Coordinator"
  },
  {
    "FirstName": "Jen L.",
    "LastName": "Stevens",
    "sites": ["BURL"],
    "Position": "Compassion Coordinator"
  },
  {
    "FirstName": "Sue",
    "LastName": "VanEgdom",
    "sites": ["HMAN"],
    "Email": "sue.vanegdom@themeetinghouse.com",
    "Position": "Compassion Coordinator"
  },
  {
    "FirstName": "Ruth",
    "LastName": "Wagner",
    "sites": ["NMKT"],
    "Position": "Compassion Coordinator"
  },
  {
    "FirstName": "April",
    "LastName": "Yorke",
    "sites": ["OTTA"],
    "Position": "Compassion Coordinator"
  },
  {
    "FirstName": "Amanda",
    "LastName": "Shaw",
    "sites": ["PRSN"],
    "Position": "Compassion Coordinator"
  },
  {
    "FirstName": "Shyamala",
    "LastName": "Pierce",
    "sites": ["RHLL"],
    "Email": "shyamala.pierce@themeetinghouse.com",
    "Position": "Compassion Coordinator"
  },
  {
    "FirstName": "Cristal",
    "LastName": "Laanstra",
    "sites": ["SAND"],
    "Email": "compassion.sandbanks@themeetinghouse.com",
    "Position": "Compassion Coordinator"
  },
  {
    "FirstName": "Kareema",
    "LastName": "Giscombe-Bartley",
    "sites": ["BRAM"],
    "Position": "Compassion Coordinator"
  },
  {
    "FirstName": "Terri",
    "LastName": "Busch",
    "sites": ["HMAN"],
    "Position": "Compassion Coordinator"
  },
  {
    "FirstName": "Danielle",
    "LastName": "Fry",
    "sites": ["HMDT"],
    "Position": "Compassion Coordinator"
  },
  {
    "FirstName": "Sandra",
    "LastName": "Albione",
    "sites": ["RHLL"],
    "Email": "sandra.albione@themeetinghouse.com",
    "Position": "Compassion Coordinator"
  },
  {
    "FirstName": "Jasmine",
    "LastName": "Wong",
    "sites": ["TOBC"],
    "Email": "jasmine.wong@themeetinghouse.com",
    "Position": "Compassion Coordinator"
  },
  {
    "FirstName": "Erica",
    "LastName": "Blekkenhorst",
    "sites": ["TODT"],
    "Email": "erica.blekkenhorst@themeetinghouse.com",
    "Position": "Compassion Coordinator"
  },
  {
    "FirstName": "Kat",
    "LastName": "Misztal-McCubbing",
    "sites": ["TOHP"],
    "Position": "Compassion Coordinator"
  },
  {
    "FirstName": "Dan",
    "LastName": "Klass",
    "sites": ["WAT"],
    "Position": "Compassion Coordinator"
  },
  {
    "FirstName": "Denis",
    "LastName": "Audette",
    "sites": ["OWSN"],
    "Email": "denis.audette@themeetinghouse.com",
    "Position": "Community Coordinator"
  },
  {
    "FirstName": "Janette",
    "LastName": "Cridland",
    "sites": ["ALLI"],
    "Email": "alliston.connect@themeetinghouse.com",
    "Position": "Connect Coordinator"
  },
  {
    "FirstName": "Graham",
    "LastName": "Elder",
    "sites": ["BRAM"],
    "Position": "Connect Coordinator"
  },
  {
    "FirstName": "Cathy",
    "LastName": "Ralph",
    "sites": ["BURL"],
    "Position": "Connect Coordinator"
  },
  {
    "FirstName": "Jessica-Rae",
    "LastName": "Linzel",
    "sites": ["OTTA"],
    "Position": "Connect Coordinator"
  },
  {
    "FirstName": "Nancy",
    "LastName": "Sergeant",
    "sites": ["SAND"],
    "Email": "sandbanks.connect@themeetinghouse.com",
    "Position": "Connect Coordinator"
  },
  {
    "FirstName": "Julie",
    "LastName": "Riley",
    "sites": ["TOBC"],
    "Position": "Connect Coordinator"
  },
  {
    "FirstName": "Scott",
    "LastName": "Mealey",
    "sites": ["TODT"],
    "Position": "Connect Coordinator"
  },
  {
    "FirstName": "Teresa",
    "LastName": "Kotsopoulos",
    "sites": ["ALLI"],
    "Email": "alliston.kidmax@themeetinghouse.com",
    "Position": "Kidmax Coordinator"
  },
  {
    "FirstName": "Brittany",
    "LastName": "Scott",
    "sites": ["BRAM"],
    "Email": "brittany.chisholm@themeetinghouse.com",
    "Position": "Kidmax Coordinator"
  },
  {
    "FirstName": "Laura",
    "LastName": "Wassink",
    "sites": ["BRFD"],
    "Email": "laura.wassink@themeetinghouse.com",
    "Position": "Kidmax Coordinator"
  },
  {
    "FirstName": "Lauren",
    "LastName": "Webster",
    "sites": ["BURL"],
    "Email": "lauren.webster@themeetinghouse.com",
    "Position": "Kidmax Coordinator"
  },
  {
    "FirstName": "Jacqueline",
    "LastName": "Wilcox",
    "sites": ["HMAN"],
    "Email": "jacqueline.wilcox@themeetinghouse.com",
    "Position": "Kidmax Coordinator"
  },
  {
    "FirstName": "Emily",
    "LastName": "Van Kampen",
    "sites": ["HMDT"],
    "Email": "emily.vankampen@themeetinghouse.com",
    "Position": "Kidmax Coordinator"
  },
  {
    "FirstName": "Wendy",
    "LastName": "Cuell",
    "sites": ["HMMT"],
    "Position": "Kidmax Coordinator"
  },
  {
    "FirstName": "Jenn",
    "LastName": "Kuntz",
    "sites": ["KIT"],
    "Email": "Jenn.kuntz@themeetinghouse.com",
    "Position": "Kidmax Coordinator"
  },
  {
    "FirstName": "Kate",
    "LastName": "Nixon",
    "sites": ["LOND"],
    "Email": "kate.nixon@themeetinghouse.com",
    "Position": "Kidmax Coordinator"
  },
  {
    "FirstName": "Jacqueline",
    "LastName": "Lo",
    "sites": ["NMKT"],
    "Email": "jacqueline.lo@themeetinghouse.com",
    "Position": "Kidmax Coordinator"
  },
  {
    "FirstName": "Tenika",
    "LastName": "Millington",
    "sites": ["NMKT"],
    "Position": "Kidmax Coordinator"
  },
  {
    "FirstName": "Darcie",
    "LastName": "Dow",
    "sites": ["OTTA"],
    "Email": "darcie.dow@themeetinghouse.com",
    "Position": "Kidmax Coordinator"
  },
  {
    "FirstName": "Amy M.",
    "LastName": "Langeman",
    "sites": ["OWSN"],
    "Email": "amy.langeman@themeetinghouse.com",
    "Position": "Kidmax Coordinator"
  },
  {
    "FirstName": "Christie-Lynn",
    "LastName": "Constable",
    "sites": ["PAR"],
    "Position": "Kidmax Coordinator"
  },
  {
    "FirstName": "Rachelle",
    "LastName": "DeBoer",
    "sites": ["PAR"],
    "Email": "parrysound.Kidmax@themeetinghouse.com",
    "Position": "Kidmax Coordinator"
  },
  {
    "FirstName": "Jenny",
    "LastName": "Shepherd",
    "sites": ["SAND"],
    "Email": "sandbanks.kidmax@themeetinghouse.com",
    "Position": "Kidmax Coordinator"
  },
  {
    "FirstName": "Janis",
    "LastName": "Hiscock",
    "sites": ["TOBC"],
    "Email": "janis.hiscock@themeetinghouse.com",
    "Position": "Kidmax Coordinator"
  },
  {
    "FirstName": "Jacob",
    "LastName": "Winter",
    "sites": ["TODT"],
    "Email": "jacob.winter@themeetinghouse.com",
    "Position": "Kidmax Coordinator"
  },
  {
    "FirstName": "Meghan",
    "LastName": "Walter",
    "sites": ["TOHP"],
    "Email": "meghan.walter@themeetinghouse.com",
    "Position": "Kidmax Coordinator"
  },
  {
    "FirstName": "Sarah",
    "LastName": "Mahimwala",
    "sites": ["TOUP"],
    "Email": "sarah.mahimwala@themeetinghouse.com",
    "Position": "Kidmax Coordinator"
  },
  {
    "FirstName": "Esther",
    "LastName": "Hazzard",
    "sites": ["BRAM"],
    "Email": "esther.hazzard@themeetinghouse.com",
    "Position": "Music Coordinator"
  },
  {
    "FirstName": "Dwayne",
    "LastName": "Jackson",
    "sites": ["BRAM"],
    "Email": "dwayne.jackson@themeetinghouse.com",
    "Position": "Music Coordinator"
  },
  {
    "FirstName": "Bram",
    "LastName": "Van den Heuvel",
    "sites": ["BRFD"],
    "Position": "Music Coordinator"
  },
  {
    "FirstName": "Adam",
    "LastName": "Davidson",
    "sites": ["BURL"],
    "Position": "Music Coordinator"
  },
  {
    "FirstName": "Steve",
    "LastName": "Green",
    "sites": ["HMAN"],
    "Email": "steve.green@themeetinghouse.com",
    "Position": "Music Coordinator"
  },
  {
    "FirstName": "Nathan J.",
    "LastName": "Scott",
    "sites": ["HMDT"],
    "Email": "Nathan.scott@themeetinghouse.com",
    "Position": "Music Coordinator"
  },
  {
    "FirstName": "Ruth",
    "LastName": "Wright",
    "sites": ["ALLI"],
    "Email": "ruth.wright@themeetinghouse.com",
    "Position": "Music Coordinator"
  },
  {
    "FirstName": "Steve",
    "LastName": "Samuels",
    "sites": ["HMMT"],
    "Position": "Music Coordinator"
  },
  {
    "FirstName": "Laura",
    "LastName": "Driedger",
    "sites": ["KIT"],
    "Email": "laura.driedger@themeetinghouse.com",
    "Position": "Music Coordinator"
  },
  {
    "FirstName": "Stephanie",
    "LastName": "Prendergast",
    "sites": ["LOND"],
    "Email": "stephanie.prendergast@themeetinghouse.com",
    "Position": "Music Coordinator"
  },
  {
    "FirstName": "William",
    "LastName": "Dyer",
    "sites": ["NMKT"],
    "Position": "Music Coordinator"
  },
  {
    "FirstName": "Mike",
    "LastName": "Walker",
    "sites": ["NMKT"],
    "Position": "Music Coordinator"
  },
  {
    "FirstName": "Carlo A.",
    "LastName": "Verdicchio Tayler",
    "sites": ["OTTA"],
    "Email": "carlo.verdicchio@themeetinghouse.com",
    "Position": "Music Coordinator"
  },
  {
    "FirstName": "Bernie",
    "LastName": "Chan",
    "sites": ["RHLL"],
    "Email": "bernard.chan@themeetinghouse.com",
    "Position": "Music Coordinator"
  },
  {
    "FirstName": "Bob",
    "LastName": "Snider",
    "sites": ["SAND"],
    "Email": "sandbanks.music@themeetinghouse.com",
    "Position": "Music Coordinator"
  },
  {
    "FirstName": "Matt",
    "LastName": "Phinney",
    "sites": ["TOBC"],
    "Position": "Music Coordinator"
  },
  {
    "FirstName": "Nathan A.",
    "LastName": "Snelgrove",
    "sites": ["TODT"],
    "Position": "Music Coordinator"
  },
  {
    "FirstName": "Becky",
    "LastName": "Voll",
    "sites": ["TOHP"],
    "Position": "Music Coordinator"
  },
  {
    "FirstName": "Keltan",
    "LastName": "Dakins",
    "sites": ["TOUP"],
    "Position": "Music Coordinator"
  },
  {
    "FirstName": "Emily",
    "LastName": "Piche",
    "sites": ["WAT"],
    "Position": "Music Coordinator"
  },
  {
    "FirstName": "Brent",
    "LastName": "Babcock",
    "sites": ["SAND"],
    "Email": "brent.babcock@themeetinghouse.com",
    "Position": "Sandbanks Lead Pastor"
  },
  {
    "FirstName": "Don",
    "LastName": "Walcott",
    "sites": ["SAND"],
    "Email": "don.walcott@themeetinghouse.com",
    "Position": "Sandbanks Associate Pastor"
  },
  {
    "FirstName": "Scott",
    "LastName": "McConnell",
    "sites": ["BRAM"],
    "Email": "scott.mcconnell@themeetinghouse.com",
    "Position": "Weekend Service Producer"
  },
  {
    "FirstName": "Joyce",
    "LastName": "Baker",
    "sites": ["BRFD"],
    "Email": "joyce.baker@themeetinghouse.com",
    "Position": "Weekend Service Producer"
  },
  {
    "FirstName": "Jamie",
    "LastName": "Teeple",
    "sites": ["BURL"],
    "Position": "Weekend Service Producer"
  },
  {
    "FirstName": "Greg",
    "LastName": "Best",
    "sites": ["HMAN"],
    "Email": "greg.best@themeetinghouse.com",
    "Position": "Weekend Service Producer"
  },
  {
    "FirstName": "Jared",
    "LastName": "Van Huizen",
    "sites": ["HMDT"],
    "Email": "jared.vanhuizen@themeetinghouse.com",
    "Position": "Weekend Service Producer"
  },
  {
    "FirstName": "Carolina",
    "LastName": "Bartholomew",
    "sites": ["HMMT"],
    "Email": "carolina.bartholomew@themeetinghouse.com",
    "Position": "Weekend Service Producer"
  },
  {
    "FirstName": "Steve",
    "LastName": "Jarnick",
    "sites": ["KIT"],
    "Email": "steve.jarnick@themeetinghouse.com",
    "Position": "Weekend Service Producer"
  },
  {
    "FirstName": "Sheryl",
    "LastName": "Bailey",
    "sites": ["LOND"],
    "Email": "sheryl.bailey@themeetinghouse.com",
    "Position": "Weekend Service Producer"
  },
  {
    "FirstName": "Sarah",
    "LastName": "Dyer",
    "sites": ["NMKT"],
    "Email": "sarah.dyer@themeetinghouse.com",
    "Position": "Weekend Service Producer"
  },
  {
    "FirstName": "Fiona",
    "LastName": "Lau",
    "sites": ["OTTA"],
    "Position": "Weekend Service Producer"
  },
  {
    "FirstName": "Daniel",
    "LastName": "VanderVeen",
    "sites": ["OTTA"],
    "Position": "Weekend Service Producer"
  },
  {
    "FirstName": "Anthony",
    "LastName": "Mak",
    "sites": ["RHLL"],
    "Position": "Weekend Service Producer"
  },
  {
    "FirstName": "Kelly",
    "LastName": "Mak",
    "sites": ["RHLL"],
    "Email": "Kelly.Mak@themeetinghouse.com",
    "Position": "Weekend Service Producer"
  },
  {
    "FirstName": "Hazel",
    "LastName": "Cheng",
    "sites": ["TOBC"],
    "Email": "hazel.cheng@themeetinghouse.com",
    "Position": "Weekend Service Producer"
  },
  {
    "FirstName": "Josh",
    "LastName": "Cole",
    "sites": ["TODT"],
    "Email": "josh.cole@themeetinghouse.com",
    "Position": "Weekend Service Producer"
  },
  {
    "FirstName": "Ronny",
    "LastName": "Juarez",
    "sites": ["TOHP"],
    "Email": "ronny.juarez@themeetinghouse.com",
    "Position": "Weekend Service Producer"
  },
  {
    "FirstName": "Russ",
    "LastName": "Skinner",
    "sites": ["TOUP"],
    "Email": "russ.skinner@themeetinghouse.com",
    "Position": "Weekend Service Producer"
  },
  {
    "FirstName": "Sarah",
    "LastName": "Stratton-Snyder",
    "sites": ["BRFD"],
    "Email": "sarah.strattonsnyder@themeetinghouse.com",
    "Position": "Welcome Coordinator"
  },
  {
    "FirstName": "Lisa",
    "LastName": "Collins",
    "sites": ["HMAN"],
    "Position": "Welcome Coordinator"
  },
  {
    "FirstName": "Jason",
    "LastName": "Lise",
    "sites": ["HMDT"],
    "Position": "Welcome Coordinator"
  },
  {
    "FirstName": "Melissa",
    "LastName": "Beldman",
    "sites": ["LOND"],
    "Email": "melissa.beldman@themeetinghouse.com",
    "Position": "Welcome Coordinator"
  },
  {
    "FirstName": "Debbie",
    "LastName": "Tindale",
    "sites": ["NMKT"],
    "Position": "Welcome Coordinator"
  },
  {
    "FirstName": "Bill",
    "LastName": "Konoval",
    "sites": ["PAR"],
    "Position": "Welcome Coordinator"
  },
  {
    "FirstName": "Tracy",
    "LastName": "Konoval",
    "sites": ["PAR"],
    "Position": "Welcome Coordinator"
  },
  {
    "FirstName": "Angela",
    "LastName": "Kong",
    "sites": ["RHLL"],
    "Position": "Welcome Coordinator"
  },
  {
    "FirstName": "Ara",
    "LastName": "Ehamparam",
    "sites": ["TOHP"],
    "Position": "Welcome Coordinator"
  },
  {
    "FirstName": "Clara",
    "LastName": "Wong",
    "sites": ["TOUP"],
    "Position": "Welcome Coordinator"
  },
  {
    "FirstName": "Colleen",
    "LastName": "Johnson",
    "sites": ["ALLI"],
    "Email": "alliston.youth@themeetinghouse.com",
    "Position": "Youth Coordinator"
  },
  {
    "FirstName": "Amie",
    "LastName": "Medeiros",
    "sites": ["BRAM"],
    "Position": "Youth Coordinator"
  },
  {
    "FirstName": "Joshua",
    "LastName": "Woodward",
    "sites": ["BRFD"],
    "Email": "josh.woodward@themeetinghouse.com",
    "Position": "Youth Coordinator"
  },
  {
    "FirstName": "Hannah",
    "LastName": "Froese",
    "sites": ["BURL"],
    "Email": "hannah.froese@themeetinghouse.com",
    "Position": "Youth Coordinator"
  },
  {
    "FirstName": "Marshall",
    "LastName": "Lewis",
    "sites": ["HMDT"],
    "Position": "Youth Coordinator"
  },
  {
    "FirstName": "Nick",
    "LastName": "Barone",
    "sites": ["HMMT"],
    "Position": "Youth Coordinator"
  },
  {
    "FirstName": "T.J.",
    "LastName": "Zielman",
    "sites": ["LOND"],
    "Email": "tj.zielman@themeetinghouse.com",
    "Position": "Youth Coordinator"
  },
  {
    "FirstName": "Angela",
    "LastName": "Rose",
    "sites": ["NMKT"],
    "Email": "angela.rose@themeetinghouse.com",
    "Position": "Youth Coordinator"
  },
  {
    "FirstName": "Aaron",
    "LastName": "Webber",
    "sites": ["OTTA"],
    "Email": "aaron.webber@themeetinghouse.com",
    "Position": "Youth Coordinator"
  },
  {
    "FirstName": "Hanna",
    "LastName": "Coppes",
    "sites": ["PRSN"],
    "Email": "hanna.coppes@themeetinghouse.com",
    "Position": "Youth Coordinator"
  },
  {
    "FirstName": "Adrienne T.",
    "LastName": "Sulistyo",
    "sites": ["RHLL"],
    "Email": "adrienne.sulistyo@themeetinghouse.com",
    "Position": "Youth Coordinator"
  },
  {
    "FirstName": "Carol",
    "LastName": "Babcock",
    "sites": ["SAND"],
    "Position": "Youth Coordinator"
  },
  {
    "FirstName": "Liz",
    "LastName": "Dale",
    "sites": ["TODT"],
    "Email": "liz.dale@themeetinghouse.com",
    "Position": "Youth Coordinator"
  },
  {
    "FirstName": "Alyssa",
    "LastName": "Esparaz",
    "sites": ["TOUP"],
    "Email": "alyssa.esparaz@themeetinghouse.com",
    "Position": "Youth Coordinator"
  }
 ]